Lomino/Lomino.py
Lomino/__init__.py
Lomino-1.0.1.dist-info/METADATA
Lomino-1.0.1.dist-info/WHEEL
Lomino-1.0.1.dist-info/top_level.txt
Lomino-1.0.1.dist-info/RECORD
