Metadata-Version: 2.1
Name: Lomino
Version: 1.0.1
Summary: Amino Api Library
Home-page: https://github.com/L0Rd5/Lomino/tree/main/Lomino
Download-URL: https://github.com/L0Rd5/Lomino/archive/refs/heads/main.zip
Author: L0Rd5
License: MIT
Keywords: Amino,python,python3,python3.x,L0Rd5,Lord,Lomino,lomino,Lomino pythonbots,narvii
Requires-Dist: requests
Requires-Dist: setuptools
Requires-Dist: websocket-client
Requires-Dist: datetime
